affinegap-1.12.dist-info/METADATA
affinegap-1.12.dist-info/WHEEL
affinegap-1.12.dist-info/RECORD
affinegap-1.12.dist-info/LICENSE
affinegap-1.12.dist-info/top_level.txt
affinegap/__init__.py
affinegap/affinegap.cpython-36m-x86_64-linux-gnu.so
